.gitignore
LICENSE
README.md
_config.yml
setup.py
qmvpa/__init__.py
qmvpa/classification.py
qmvpa/factor.py
qmvpa/preproc.py
qmvpa/rsa.py
qmvpa/utils.py
qmvpa/vis.py
qmvpa.egg-info/PKG-INFO
qmvpa.egg-info/SOURCES.txt
qmvpa.egg-info/dependency_links.txt
qmvpa.egg-info/not-zip-safe
qmvpa.egg-info/requires.txt
qmvpa.egg-info/top_level.txt