Metadata-Version: 1.0
Name: qmvpa
Version: 0.52
Summary: my MVPA package
Home-page: https://github.com/qihongl/qmvpa
Author: Qihong Lu
Author-email: lvqihong1992@gmail.com
License: MIT
Keywords: neuroimaging,machine learning
Platform: UNKNOWN
